{"trial_id": "0092", "hyperparameters": {"space": [{"class_name": "Int", "config": {"name": "units", "default": null, "conditions": [], "min_value": 2, "max_value": 240, "step": 2, "sampling": "linear"}}], "values": {"units": 186}}, "metrics": {"metrics": {"loss": {"direction": "min", "observations": [{"value": [0.00023708606022410095], "step": 32}]}, "val_loss": {"direction": "min", "observations": [{"value": [0.0017379922792315483], "step": 32}]}}}, "score": 0.0017379922792315483, "best_step": 32, "status": "COMPLETED", "message": null}