{"trial_id": "0017", "hyperparameters": {"space": [{"class_name": "Int", "config": {"name": "units", "default": null, "conditions": [], "min_value": 2, "max_value": 240, "step": 2, "sampling": "linear"}}], "values": {"units": 36}}, "metrics": {"metrics": {"loss": {"direction": "min", "observations": [{"value": [0.00019105360843241215], "step": 84}]}, "val_loss": {"direction": "min", "observations": [{"value": [0.023333756253123283], "step": 84}]}}}, "score": 0.023333756253123283, "best_step": 84, "status": "COMPLETED", "message": null}