{"trial_id": "0025", "hyperparameters": {"space": [{"class_name": "Int", "config": {"name": "units", "default": null, "conditions": [], "min_value": 2, "max_value": 240, "step": 2, "sampling": "linear"}}], "values": {"units": 52}}, "metrics": {"metrics": {"loss": {"direction": "min", "observations": [{"value": [0.0017303802305832505], "step": 32}]}, "val_loss": {"direction": "min", "observations": [{"value": [0.005092734005302191], "step": 32}]}}}, "score": 0.005092734005302191, "best_step": 32, "status": "COMPLETED", "message": null}