{"trial_id": "0066", "hyperparameters": {"space": [{"class_name": "Int", "config": {"name": "units", "default": null, "conditions": [], "min_value": 2, "max_value": 240, "step": 2, "sampling": "linear"}}], "values": {"units": 134}}, "metrics": {"metrics": {"loss": {"direction": "min", "observations": [{"value": [0.00025252907653339207], "step": 47}]}, "val_loss": {"direction": "min", "observations": [{"value": [0.0029502168763428926], "step": 47}]}}}, "score": 0.0029502168763428926, "best_step": 47, "status": "COMPLETED", "message": null}