{"trial_id": "0023", "hyperparameters": {"space": [{"class_name": "Int", "config": {"name": "units", "default": null, "conditions": [], "min_value": 2, "max_value": 240, "step": 2, "sampling": "linear"}}], "values": {"units": 48}}, "metrics": {"metrics": {"loss": {"direction": "min", "observations": [{"value": [0.0011035088682547212], "step": 38}]}, "val_loss": {"direction": "min", "observations": [{"value": [0.004322420340031385], "step": 38}]}}}, "score": 0.004322420340031385, "best_step": 38, "status": "COMPLETED", "message": null}