{"trial_id": "0100", "hyperparameters": {"space": [{"class_name": "Int", "config": {"name": "units", "default": null, "conditions": [], "min_value": 2, "max_value": 240, "step": 2, "sampling": "linear"}}], "values": {"units": 202}}, "metrics": {"metrics": {"loss": {"direction": "min", "observations": [{"value": [0.000325113971484825], "step": 99}]}, "val_loss": {"direction": "min", "observations": [{"value": [0.0006318094674497843], "step": 99}]}}}, "score": 0.0006318094674497843, "best_step": 99, "status": "COMPLETED", "message": null}