{"trial_id": "0094", "hyperparameters": {"space": [{"class_name": "Int", "config": {"name": "units", "default": null, "conditions": [], "min_value": 2, "max_value": 240, "step": 2, "sampling": "linear"}}], "values": {"units": 190}}, "metrics": {"metrics": {"loss": {"direction": "min", "observations": [{"value": [0.00015471714141312987], "step": 62}]}, "val_loss": {"direction": "min", "observations": [{"value": [0.0008829192374832928], "step": 62}]}}}, "score": 0.0008829192374832928, "best_step": 62, "status": "COMPLETED", "message": null}