{"trial_id": "0008", "hyperparameters": {"space": [{"class_name": "Int", "config": {"name": "units", "default": null, "conditions": [], "min_value": 2, "max_value": 240, "step": 2, "sampling": "linear"}}], "values": {"units": 18}}, "metrics": {"metrics": {"loss": {"direction": "min", "observations": [{"value": [0.0010483624646440148], "step": 146}]}, "val_loss": {"direction": "min", "observations": [{"value": [0.003349709790199995], "step": 146}]}}}, "score": 0.003349709790199995, "best_step": 146, "status": "COMPLETED", "message": null}