{"trial_id": "0054", "hyperparameters": {"space": [{"class_name": "Int", "config": {"name": "units", "default": null, "conditions": [], "min_value": 2, "max_value": 240, "step": 2, "sampling": "linear"}}], "values": {"units": 110}}, "metrics": {"metrics": {"loss": {"direction": "min", "observations": [{"value": [0.00011616892152233049], "step": 93}]}, "val_loss": {"direction": "min", "observations": [{"value": [0.011340649798512459], "step": 93}]}}}, "score": 0.011340649798512459, "best_step": 93, "status": "COMPLETED", "message": null}