{"trial_id": "0018", "hyperparameters": {"space": [{"class_name": "Int", "config": {"name": "units", "default": null, "conditions": [], "min_value": 2, "max_value": 240, "step": 2, "sampling": "linear"}}], "values": {"units": 38}}, "metrics": {"metrics": {"loss": {"direction": "min", "observations": [{"value": [0.00012642853835131973], "step": 143}]}, "val_loss": {"direction": "min", "observations": [{"value": [0.030068909749388695], "step": 143}]}}}, "score": 0.030068909749388695, "best_step": 143, "status": "COMPLETED", "message": null}