{"trial_id": "0110", "hyperparameters": {"space": [{"class_name": "Int", "config": {"name": "units", "default": null, "conditions": [], "min_value": 2, "max_value": 240, "step": 2, "sampling": "linear"}}], "values": {"units": 222}}, "metrics": {"metrics": {"loss": {"direction": "min", "observations": [{"value": [0.00028172164456918836], "step": 36}]}, "val_loss": {"direction": "min", "observations": [{"value": [0.0008314017322845757], "step": 36}]}}}, "score": 0.0008314017322845757, "best_step": 36, "status": "COMPLETED", "message": null}