{"trial_id": "0025", "hyperparameters": {"space": [{"class_name": "Int", "config": {"name": "units", "default": null, "conditions": [], "min_value": 2, "max_value": 240, "step": 2, "sampling": "linear"}}], "values": {"units": 52}}, "metrics": {"metrics": {"loss": {"direction": "min", "observations": [{"value": [0.0003116432926617563], "step": 85}]}, "val_loss": {"direction": "min", "observations": [{"value": [0.0024178146850317717], "step": 85}]}}}, "score": 0.0024178146850317717, "best_step": 85, "status": "COMPLETED", "message": null}