{"trial_id": "0021", "hyperparameters": {"space": [{"class_name": "Int", "config": {"name": "units", "default": null, "conditions": [], "min_value": 2, "max_value": 240, "step": 2, "sampling": "linear"}}], "values": {"units": 44}}, "metrics": {"metrics": {"loss": {"direction": "min", "observations": [{"value": [0.0006200041389092803], "step": 42}]}, "val_loss": {"direction": "min", "observations": [{"value": [0.002613362157717347], "step": 42}]}}}, "score": 0.002613362157717347, "best_step": 42, "status": "COMPLETED", "message": null}