{"trial_id": "0081", "hyperparameters": {"space": [{"class_name": "Int", "config": {"name": "units", "default": null, "conditions": [], "min_value": 2, "max_value": 240, "step": 2, "sampling": "linear"}}], "values": {"units": 164}}, "metrics": {"metrics": {"loss": {"direction": "min", "observations": [{"value": [0.00013276163372211158], "step": 68}]}, "val_loss": {"direction": "min", "observations": [{"value": [0.006326875649392605], "step": 68}]}}}, "score": 0.006326875649392605, "best_step": 68, "status": "COMPLETED", "message": null}