{"trial_id": "0028", "hyperparameters": {"space": [{"class_name": "Int", "config": {"name": "units", "default": null, "conditions": [], "min_value": 2, "max_value": 240, "step": 2, "sampling": "linear"}}], "values": {"units": 58}}, "metrics": {"metrics": {"loss": {"direction": "min", "observations": [{"value": [0.00047895347233861685], "step": 64}]}, "val_loss": {"direction": "min", "observations": [{"value": [0.0009422556613571942], "step": 64}]}}}, "score": 0.0009422556613571942, "best_step": 64, "status": "COMPLETED", "message": null}