{"trial_id": "0001", "hyperparameters": {"space": [{"class_name": "Int", "config": {"name": "units", "default": null, "conditions": [], "min_value": 2, "max_value": 240, "step": 2, "sampling": "linear"}}], "values": {"units": 4}}, "metrics": {"metrics": {"loss": {"direction": "min", "observations": [{"value": [0.0010634674690663815], "step": 188}]}, "val_loss": {"direction": "min", "observations": [{"value": [0.055548857897520065], "step": 188}]}}}, "score": 0.055548857897520065, "best_step": 188, "status": "COMPLETED", "message": null}