{"trial_id": "0083", "hyperparameters": {"space": [{"class_name": "Int", "config": {"name": "units", "default": null, "conditions": [], "min_value": 2, "max_value": 240, "step": 2, "sampling": "linear"}}], "values": {"units": 168}}, "metrics": {"metrics": {"loss": {"direction": "min", "observations": [{"value": [0.0001649342739256099], "step": 72}]}, "val_loss": {"direction": "min", "observations": [{"value": [0.0003730136959347874], "step": 72}]}}}, "score": 0.0003730136959347874, "best_step": 72, "status": "COMPLETED", "message": null}