{"trial_id": "0078", "hyperparameters": {"space": [{"class_name": "Int", "config": {"name": "units", "default": null, "conditions": [], "min_value": 2, "max_value": 240, "step": 2, "sampling": "linear"}}], "values": {"units": 158}}, "metrics": {"metrics": {"loss": {"direction": "min", "observations": [{"value": [0.00010523395030759275], "step": 96}]}, "val_loss": {"direction": "min", "observations": [{"value": [0.0002469478058628738], "step": 96}]}}}, "score": 0.0002469478058628738, "best_step": 96, "status": "COMPLETED", "message": null}