{"trial_id": "0050", "hyperparameters": {"space": [{"class_name": "Int", "config": {"name": "units", "default": null, "conditions": [], "min_value": 2, "max_value": 240, "step": 2, "sampling": "linear"}}], "values": {"units": 102}}, "metrics": {"metrics": {"loss": {"direction": "min", "observations": [{"value": [0.00020554834918584675], "step": 68}]}, "val_loss": {"direction": "min", "observations": [{"value": [0.006184181198477745], "step": 68}]}}}, "score": 0.006184181198477745, "best_step": 68, "status": "COMPLETED", "message": null}