{"trial_id": "0065", "hyperparameters": {"space": [{"class_name": "Int", "config": {"name": "units", "default": null, "conditions": [], "min_value": 2, "max_value": 240, "step": 2, "sampling": "linear"}}], "values": {"units": 132}}, "metrics": {"metrics": {"loss": {"direction": "min", "observations": [{"value": [0.00033089087810367346], "step": 30}]}, "val_loss": {"direction": "min", "observations": [{"value": [0.0007104658870957792], "step": 30}]}}}, "score": 0.0007104658870957792, "best_step": 30, "status": "COMPLETED", "message": null}