{"trial_id": "0096", "hyperparameters": {"space": [{"class_name": "Int", "config": {"name": "units", "default": null, "conditions": [], "min_value": 2, "max_value": 240, "step": 2, "sampling": "linear"}}], "values": {"units": 194}}, "metrics": {"metrics": {"loss": {"direction": "min", "observations": [{"value": [0.0001283502933802083], "step": 63}]}, "val_loss": {"direction": "min", "observations": [{"value": [0.002286636270582676], "step": 63}]}}}, "score": 0.002286636270582676, "best_step": 63, "status": "COMPLETED", "message": null}