{"trial_id": "0110", "hyperparameters": {"space": [{"class_name": "Int", "config": {"name": "units", "default": null, "conditions": [], "min_value": 2, "max_value": 240, "step": 2, "sampling": "linear"}}], "values": {"units": 222}}, "metrics": {"metrics": {"loss": {"direction": "min", "observations": [{"value": [0.0002128830092260614], "step": 38}]}, "val_loss": {"direction": "min", "observations": [{"value": [0.005705882795155048], "step": 38}]}}}, "score": 0.005705882795155048, "best_step": 38, "status": "COMPLETED", "message": null}