{"trial_id": "0049", "hyperparameters": {"space": [{"class_name": "Int", "config": {"name": "units", "default": null, "conditions": [], "min_value": 2, "max_value": 240, "step": 2, "sampling": "linear"}}], "values": {"units": 100}}, "metrics": {"metrics": {"loss": {"direction": "min", "observations": [{"value": [0.0001599074457772076], "step": 59}]}, "val_loss": {"direction": "min", "observations": [{"value": [0.0009109011152759194], "step": 59}]}}}, "score": 0.0009109011152759194, "best_step": 59, "status": "COMPLETED", "message": null}